betterfftw/__init__.py
betterfftw/core.py
betterfftw/interface.py
betterfftw/planning.py
betterfftw-0.1.3.dist-info/licenses/LICENSE
betterfftw-0.1.3.dist-info/METADATA
betterfftw-0.1.3.dist-info/WHEEL
betterfftw-0.1.3.dist-info/top_level.txt
betterfftw-0.1.3.dist-info/RECORD
