Metadata-Version: 2.4
Name: betterfftw
Version: 0.1.3
Summary: High-performance, user-friendly wrapper for FFTW in Python
Author-email: Sebastian Griego <sebastianngriego@gmail.com>
License-Expression: GPL-3.0-or-later
Project-URL: Homepage, https://github.com/sebastian-griego/betterfftw
Classifier: Programming Language :: Python :: 3
Classifier: Operating System :: OS Independent
Classifier: Topic :: Scientific/Engineering :: Mathematics
Classifier: Intended Audience :: Science/Research
Requires-Python: >=3.7
License-File: LICENSE
Requires-Dist: numpy>=1.17.0
Requires-Dist: scipy>=1.3.0
Requires-Dist: pyfftw>=0.12.0
Requires-Dist: psutil>=5.6.0
Provides-Extra: dev
Requires-Dist: matplotlib; extra == "dev"
Requires-Dist: pytest>=6.0; extra == "dev"
Requires-Dist: black; extra == "dev"
Dynamic: license-file
